<?xml version="1.0" encoding="utf-8" ?><dwsync><file name="Benchmark.php" server="milaforum.com" local="3404801676" remote="12000067772" /><file name="CodeIgniter.php" server="milaforum.com" local="3404801676" remote="12000067772" /><file name="Common.php" server="milaforum.com" local="3404801676" remote="12000067772" /><file name="Config.php" server="milaforum.com" local="3404801676" remote="12000067772" /><file name="Controller.php" server="milaforum.com" local="3404801676" remote="12000067772" /><file name="Exceptions.php" server="milaforum.com" local="3404801676" remote="12000067772" /><file name="Hooks.php" server="milaforum.com" local="3404801676" remote="12000067772" /><file name="index.html" server="milaforum.com" local="3404800358" remote="12000067772" /><file name="Input.php" server="milaforum.com" local="3404801676" remote="12000067772" /><file name="Lang.php" server="milaforum.com" local="3404801676" remote="12000067772" /><file name="Loader.php" server="milaforum.com" local="3404801676" remote="12000067772" /><file name="Model.php" server="milaforum.com" local="3404801676" remote="12000067772" /><file name="Output.php" server="milaforum.com" local="3404801676" remote="12000067772" /><file name="Router.php" server="milaforum.com" local="3404801676" remote="12000067772" /><file name="Security.php" server="milaforum.com" local="3404801676" remote="12000067772" /><file name="URI.php" server="milaforum.com" local="3404801676" remote="12000067772" /><file name="Utf8.php" server="milaforum.com" local="3404801676" remote="12000067772" /></dwsync>